akeyless_ansible/__init__.py
akeyless_ansible/plugins/__init__.py
akeyless_ansible/plugins/doc_fragments/__init__.py
akeyless_ansible/plugins/doc_fragments/accessibility.py
akeyless_ansible/plugins/doc_fragments/auth.py
akeyless_ansible/plugins/doc_fragments/connection.py
akeyless_ansible/plugins/doc_fragments/token.py
akeyless_ansible/plugins/lookup/__init__.py
akeyless_ansible/plugins/lookup/create_static_secret.py
akeyless_ansible/plugins/lookup/get_classic_key_value.py
akeyless_ansible/plugins/lookup/get_dynamic_secret_value.py
akeyless_ansible/plugins/lookup/get_pki_certificate.py
akeyless_ansible/plugins/lookup/get_rotated_secret_value.py
akeyless_ansible/plugins/lookup/get_rsa_public.py
akeyless_ansible/plugins/lookup/get_ssh_certificate.py
akeyless_ansible/plugins/lookup/get_static_secret_value.py
akeyless_ansible/plugins/lookup/list_items.py
akeyless_ansible/plugins/lookup/login.py
akeyless_ansible/plugins/lookup/update_static_secret_value.py
akeyless_ansible/plugins/module_utils/__init__.py
akeyless_ansible/plugins/module_utils/_akeyless_helper.py
akeyless_ansible/plugins/module_utils/_akeyless_module.py
akeyless_ansible/plugins/module_utils/_auth_method_api_key.py
akeyless_ansible/plugins/module_utils/_auth_method_aws_iam.py
akeyless_ansible/plugins/module_utils/_auth_method_azure_ad.py
akeyless_ansible/plugins/module_utils/_auth_method_base.py
akeyless_ansible/plugins/module_utils/_auth_method_cert.py
akeyless_ansible/plugins/module_utils/_auth_method_gcp.py
akeyless_ansible/plugins/module_utils/_auth_method_jwt.py
akeyless_ansible/plugins/module_utils/_auth_method_k8s.py
akeyless_ansible/plugins/module_utils/_auth_method_ldap.py
akeyless_ansible/plugins/module_utils/_auth_method_oci.py
akeyless_ansible/plugins/module_utils/_auth_method_oidc.py
akeyless_ansible/plugins/module_utils/_auth_method_password.py
akeyless_ansible/plugins/module_utils/_auth_method_saml.py
akeyless_ansible/plugins/module_utils/_auth_method_universal_identity.py
akeyless_ansible-1.0.4.dist-info/LICENSE.md
akeyless_ansible-1.0.4.dist-info/METADATA
akeyless_ansible-1.0.4.dist-info/WHEEL
akeyless_ansible-1.0.4.dist-info/top_level.txt
akeyless_ansible-1.0.4.dist-info/RECORD
