Metadata-Version: 2.2
Name: akeyless_ansible
Version: 1.0.4
Summary: Ansible plugins for Akeyless
Author-email: Akeyless Security <refael@akeyless.io>
License: MIT
Classifier: Programming Language :: Python :: 3
Classifier: License :: OSI Approved :: MIT License
Classifier: Operating System :: OS Independent
License-File: LICENSE.md
Requires-Dist: akeyless==4.3.0
Requires-Dist: altgraph==0.17.4
Requires-Dist: ansible==8.7.0
Requires-Dist: ansible-core==2.15.13
Requires-Dist: build==1.2.2.post1
Requires-Dist: certifi==2024.12.14
Requires-Dist: cffi==1.17.1
Requires-Dist: cryptography==44.0.0
Requires-Dist: exceptiongroup==1.2.2
Requires-Dist: future==1.0.0
Requires-Dist: importlib-resources==5.0.7
Requires-Dist: importlib_metadata==8.5.0
Requires-Dist: iniconfig==2.0.0
Requires-Dist: Jinja2==3.1.5
Requires-Dist: macholib==1.16.3
Requires-Dist: MarkupSafe==3.0.2
Requires-Dist: packaging==24.2
Requires-Dist: pluggy==1.5.0
Requires-Dist: psutil==6.1.1
Requires-Dist: pycparser==2.22
Requires-Dist: pyproject_hooks==1.2.0
Requires-Dist: pytest==8.3.4
Requires-Dist: python-dateutil==2.9.0.post0
Requires-Dist: PyYAML==6.0.2
Requires-Dist: resolvelib==1.0.1
Requires-Dist: six==1.17.0
Requires-Dist: tomli==2.2.1
Requires-Dist: urllib3==2.3.0
Requires-Dist: zipp==3.21.0
